email_management/__init__.py
email_management/config.py
email_management/email_assistant.py
email_management/email_manager.py
email_management/email_query.py
email_management/errors.py
email_management/logger.py
email_management/py.typed
email_management/types.py
email_management/assistants/__init__.py
email_management/assistants/classify_emails.py
email_management/assistants/compose_email.py
email_management/assistants/detect_phishing_for_email.py
email_management/assistants/evaluate_sender_trust_for_email.py
email_management/assistants/extract_tasks_from_emails.py
email_management/assistants/generate_follow_up_for_email.py
email_management/assistants/natural_language_query.py
email_management/assistants/prioritize_emails.py
email_management/assistants/reply.py
email_management/assistants/reply_suggestions.py
email_management/assistants/rewrite_email.py
email_management/assistants/summarize_attachments_for_email.py
email_management/assistants/summarize_thread_emails.py
email_management/assistants/summary.py
email_management/assistants/summary_multi.py
email_management/assistants/translate_email.py
email_management/auth/__init__.py
email_management/auth/base.py
email_management/auth/no_auth.py
email_management/auth/oauth2.py
email_management/auth/password.py
email_management/imap/__init__.py
email_management/imap/client.py
email_management/imap/parser.py
email_management/imap/query.py
email_management/llm/__init__.py
email_management/llm/claude.py
email_management/llm/costs.py
email_management/llm/gemini.py
email_management/llm/gpt.py
email_management/llm/groq.py
email_management/llm/model.py
email_management/llm/xai.py
email_management/models/__init__.py
email_management/models/attachment.py
email_management/models/message.py
email_management/models/subscription.py
email_management/models/task.py
email_management/smtp/__init__.py
email_management/smtp/builder.py
email_management/smtp/client.py
email_management/smtp/templates.py
email_management-0.1.4.dist-info/METADATA
email_management-0.1.4.dist-info/WHEEL
email_management-0.1.4.dist-info/licenses/LICENSE
email_management-0.1.4.dist-info/RECORD
