Metadata-Version: 2.4
Name: email_management
Version: 0.1.4
Summary: API for managing your email
License-File: LICENSE
Requires-Python: >=3.8
Requires-Dist: beautifulsoup4
Requires-Dist: langchain
Requires-Dist: langchain-anthropic
Requires-Dist: langchain-core
Requires-Dist: langchain-google-genai
Requires-Dist: langchain-groq
Requires-Dist: langchain-openai
Requires-Dist: langchain-xai
Requires-Dist: pydantic
Requires-Dist: requests
Provides-Extra: test
Requires-Dist: pytest; extra == 'test'
